traceai_smolagents/__init__.py
traceai_smolagents/_wrappers.py
traceai_smolagents/version.py
traceai_smolagents-0.1.4.dist-info/METADATA
traceai_smolagents-0.1.4.dist-info/WHEEL
traceai_smolagents-0.1.4.dist-info/RECORD
